check_python_vuln/__init__.py
check_python_vuln/__main__.py
check_python_vuln/cookie-domain-check.py
check_python_vuln/cookie-path-check.py
check_python_vuln/email_fold_dos.py
check_python_vuln/email_parseaddr_domain.py
check_python_vuln/gettext_c2py.py
check_python_vuln/hash_dos.py
check_python_vuln/http_header_injection2.py
check_python_vuln/ssl-crl-dps-dos.py
check_python_vuln/ssl-match_hostname-ipv4-trailing.py
check_python_vuln/ssl_nul_in_subjectaltnames.py
check_python_vuln/urllib_basic_auth_regex_dos.py
check_python_vuln/urllib_local_file.py
check_python_vuln/urlsplit_normalization.py
check_python_vuln/vulntools.py
check_python_vuln/data/CVE-2019-5010.pem
check_python_vuln/data/nullbytecert.pem
check_python_vuln-2020.7.1.post1.dist-info/COPYING
check_python_vuln-2020.7.1.post1.dist-info/METADATA
check_python_vuln-2020.7.1.post1.dist-info/WHEEL
check_python_vuln-2020.7.1.post1.dist-info/top_level.txt
check_python_vuln-2020.7.1.post1.dist-info/RECORD
