Metadata-Version: 2.1
Name: check-python-vuln
Version: 2020.7.1.post1
Summary: Check for Python vulnerabilities
Home-page: https://github.com/vstinner/check_python_vuln
Author: Victor Stinner
Author-email: vstinner@redhat.com
License: MIT license
Platform: UNKNOWN
Classifier: Development Status :: 4 - Beta
Classifier: Intended Audience :: Developers
Classifier: License :: OSI Approved :: MIT License
Classifier: Natural Language :: English
Classifier: Operating System :: OS Independent
Classifier: Programming Language :: Python :: 2.7
Classifier: Programming Language :: Python :: 3
